airports_analytics/__init__.py
airports_analytics/airports.txt
airports_analytics-0.2.0.dist-info/METADATA
airports_analytics-0.2.0.dist-info/WHEEL
airports_analytics-0.2.0.dist-info/RECORD
