Metadata-Version: 2.1
Name: airports_analytics
Version: 0.2.0
Summary: Airport geospacial analytics
Author: Hakan Ergan
Author-email: ergan.hakan@gmail.com
Requires-Python: >=3.10,<4.0
Classifier: Programming Language :: Python :: 3
Classifier: Programming Language :: Python :: 3.10
Classifier: Programming Language :: Python :: 3.11
Classifier: Programming Language :: Python :: 3.12
Requires-Dist: arrow (>=1.3.0,<2.0.0)
Requires-Dist: requests (>=2.31.0,<3.0.0)
